.bumpversion.cfg
LICENSE
MANIFEST.in
Makefile
README.md
pyproject.toml
setup.py
example_project_python/__init__.py
example_project_python/__main__.py
example_project_python/hello.py
example_project_python.egg-info/PKG-INFO
example_project_python.egg-info/SOURCES.txt
example_project_python.egg-info/dependency_links.txt
example_project_python.egg-info/requires.txt
example_project_python.egg-info/top_level.txt
example_project_python/tests/test_all.py