Metadata-Version: 2.1
Name: example-project-python
Version: 0.1.0
Summary: An example python project
Author-email: Your Name <Your_Email@gmail.com>
License:                                  Apache License
Project-URL: repository, https://github.com/columbiaoss/example-project-python
Classifier: Development Status :: 2 - Pre-Alpha
Classifier: Programming Language :: Python :: Implementation :: CPython
Classifier: Programming Language :: Python :: Implementation :: PyPy
Classifier: Programming Language :: Python :: 3
Classifier: Programming Language :: Python :: 3.7
Classifier: Programming Language :: Python :: 3.8
Classifier: Programming Language :: Python :: 3.9
Classifier: Programming Language :: Python :: 3.10
Classifier: Programming Language :: Python :: 3.11
Requires-Python: >=3.7
Provides-Extra: develop
License-File: LICENSE
